Compiled from "NondetGeneric.java"
class NondetGeneric {
  static final boolean $assertionsDisabled;

  NondetGeneric();
    Code:
       0: aload_0
       1: invokespecial #1                  // Method java/lang/Object."<init>":()V
       4: return

  static void callWithoutExplicitType();
    Code:
       0: invokestatic  #2                  // Method org/cprover/CProver.nondet:()Ljava/lang/Object;
       3: checkcast     #3                  // class Foo
       6: astore_0
       7: getstatic     #4                  // Field $assertionsDisabled:Z
      10: ifne          25
      13: aload_0
      14: ifnull        25
      17: new           #5                  // class java/lang/AssertionError
      20: dup
      21: invokespecial #6                  // Method java/lang/AssertionError."<init>":()V
      24: athrow
      25: return

  static void callWithoutAssigningResult();
    Code:
       0: getstatic     #4                  // Field $assertionsDisabled:Z
       3: ifne          20
       6: invokestatic  #2                  // Method org/cprover/CProver.nondet:()Ljava/lang/Object;
       9: ifnull        20
      12: new           #5                  // class java/lang/AssertionError
      15: dup
      16: invokespecial #6                  // Method java/lang/AssertionError."<init>":()V
      19: athrow
      20: return

  static {};
    Code:
       0: ldc           #7                  // class NondetGeneric
       2: invokevirtual #8                  // Method java/lang/Class.desiredAssertionStatus:()Z
       5: ifne          12
       8: iconst_1
       9: goto          13
      12: iconst_0
      13: putstatic     #4                  // Field $assertionsDisabled:Z
      16: return
}
